serial_json/__init__.py
serial_json/__meta__.py
serial_json/bytes_support.py
serial_json/dataclasses.py
serial_json/datetime_support.py
serial_json/interface.py
serial_json/numpy_support.py
serial_json/weekdays_list.py
serial_json/__pycache__/__init__.cpython-36.pyc
serial_json/__pycache__/__init__.cpython-38.pyc
serial_json/__pycache__/bytes_support.cpython-36.pyc
serial_json/__pycache__/bytes_support.cpython-38.pyc
serial_json/__pycache__/dataclasses.cpython-36.pyc
serial_json/__pycache__/dataclasses.cpython-38.pyc
serial_json/__pycache__/datetime_support.cpython-36.pyc
serial_json/__pycache__/datetime_support.cpython-38.pyc
serial_json/__pycache__/interface.cpython-36.pyc
serial_json/__pycache__/interface.cpython-38.pyc
serial_json/__pycache__/numpy_support.cpython-36.pyc
serial_json/__pycache__/numpy_support.cpython-38.pyc
serial_json/__pycache__/weekdays_list.cpython-36.pyc
serial_json/__pycache__/weekdays_list.cpython-38.pyc
serial_json-1.2.7.dist-info/LICENSE
serial_json-1.2.7.dist-info/METADATA
serial_json-1.2.7.dist-info/WHEEL
serial_json-1.2.7.dist-info/top_level.txt
serial_json-1.2.7.dist-info/RECORD
