Metadata-Version: 2.1
Name: serial-json
Version: 1.2.7
Summary: Custom json serialization support.
Home-page: https://github.com/justengel/serial_json
Author: Justin Engel
Author-email: jtengel08@gmail.com
License: Proprietary
Download-URL: https://github.com/justengel/serial_json/archive/v1.2.7.tar.gz
Keywords: JSON Serialize Deserialize numpy datetime
Platform: any
Classifier: Programming Language :: Python
Classifier: Programming Language :: Python :: 3
Classifier: Operating System :: OS Independent
